Metadata-Version: 1.0
Name: pacsretrieve
Version: 1.2.3
Summary: Interact with a PACS through an intermediary service, "pfdcm" (not included).
Home-page: https://github.com/FNNDSC/pfmisc
Author: Rudolph Pienaar
Author-email: rudolph.pienaar@gmail.com
License: MIT
Platform: UNKNOWN
